sharrow/__init__.py
sharrow/_infer_version.py
sharrow/_version.py
sharrow/accessors.py
sharrow/aster.py
sharrow/categorical.py
sharrow/dataset.py
sharrow/datastore.py
sharrow/debug.py
sharrow/digital_encoding.py
sharrow/example_data.py
sharrow/filewrite.py
sharrow/flows.py
sharrow/logging.py
sharrow/maths.py
sharrow/nested_logit.py
sharrow/omx.py
sharrow/relationships.py
sharrow/selectors.py
sharrow/shared_memory.py
sharrow/sparse.py
sharrow/table.py
sharrow/translate.py
sharrow/tree_branch.py
sharrow/viz.py
sharrow/wrappers.py
sharrow/example_data/households.csv.gz
sharrow/example_data/land_use.csv.gz
sharrow/example_data/maz_to_maz_walk.csv
sharrow/example_data/maz_to_taz.csv
sharrow/example_data/persons.csv.gz
sharrow/example_data/skims.omx
sharrow/example_data/skims.zarr/.zattrs
sharrow/example_data/skims.zarr/.zgroup
sharrow/example_data/skims.zarr/DIST/.zarray
sharrow/example_data/skims.zarr/DIST/.zattrs
sharrow/example_data/skims.zarr/DIST/0.0
sharrow/example_data/skims.zarr/DISTBIKE/.zarray
sharrow/example_data/skims.zarr/DISTBIKE/.zattrs
sharrow/example_data/skims.zarr/DISTBIKE/0.0
sharrow/example_data/skims.zarr/DISTWALK/.zarray
sharrow/example_data/skims.zarr/DISTWALK/.zattrs
sharrow/example_data/skims.zarr/DISTWALK/0.0
sharrow/example_data/skims.zarr/DRV_COM_WLK_BOARDS/.zarray
sharrow/example_data/skims.zarr/DRV_COM_WLK_BOARDS/.zattrs
sharrow/example_data/skims.zarr/DRV_COM_WLK_BOARDS/0.0.0
sharrow/example_data/skims.zarr/DRV_COM_WLK_DDIST/.zarray
sharrow/example_data/skims.zarr/DRV_COM_WLK_DDIST/.zattrs
sharrow/example_data/skims.zarr/DRV_COM_WLK_DDIST/0.0.0
sharrow/example_data/skims.zarr/DRV_COM_WLK_DTIM/.zarray
sharrow/example_data/skims.zarr/DRV_COM_WLK_DTIM/.zattrs
sharrow/example_data/skims.zarr/DRV_COM_WLK_DTIM/0.0.0
sharrow/example_data/skims.zarr/DRV_COM_WLK_FAR/.zarray
sharrow/example_data/skims.zarr/DRV_COM_WLK_FAR/.zattrs
sharrow/example_data/skims.zarr/DRV_COM_WLK_FAR/0.0.0
sharrow/example_data/skims.zarr/DRV_COM_WLK_IWAIT/.zarray
sharrow-2.14.0.dist-info/licenses/LICENSE
sharrow-2.14.0.dist-info/METADATA
sharrow-2.14.0.dist-info/WHEEL
sharrow-2.14.0.dist-info/top_level.txt
sharrow-2.14.0.dist-info/RECORD
