Metadata-Version: 2.4
Name: sharrow
Version: 2.14.0
Summary: numba for ActivitySim-style spec files
Project-URL: Documentation, https://activitysim.github.io/sharrow/
Project-URL: Repository, https://github.com/activitysim/sharrow
Keywords: activitysim,discrete choice
Classifier: License :: OSI Approved :: BSD License
Classifier: Programming Language :: Python :: 3
Classifier: Programming Language :: Python :: 3.9
Classifier: Programming Language :: Python :: 3.10
Classifier: Programming Language :: Python :: 3.11
Requires-Python: >=3.9
License-File: LICENSE
Requires-Dist: numpy>=1.19
Requires-Dist: pandas>=1.2
Requires-Dist: pyarrow
Requires-Dist: xarray
Requires-Dist: numba>=0.57
Requires-Dist: numexpr
Requires-Dist: filelock
Requires-Dist: dask
Requires-Dist: networkx
Dynamic: license-file
